medicraft/config.py
medicraft/datasets/__init__.py
medicraft/datasets/eye_scans.py
medicraft/datasets/opthal_anonymized.py
medicraft/datasets/prepare_dataset.py
medicraft/datasets/preprocess.py
medicraft/experiments/local_run_experiment.py
medicraft/experiments/old_run_experiment.py
medicraft/experiments/test_run_experiment.py
medicraft/generate_dataset_temp.py
medicraft/generate_samples.py
medicraft/main.py
medicraft/models/__init__.py
medicraft/models/classifier.py
medicraft/models/gausian_diffusion.py
medicraft/pipeline/__init__.py
medicraft/pipeline/blocks/__init__.py
medicraft/pipeline/blocks/blocks.py
medicraft/pipeline/blocks/data_dto.py
medicraft/pipeline/blocks/experiment_dto.py
medicraft/pipeline/blocks/general_dto.py
medicraft/pipeline/blocks/models_dto.py
medicraft/pipeline/blocks/output_dto.py
medicraft/pipeline/parser.py
medicraft/pipeline/pipeline.py
medicraft/run_classification_experiment.py
medicraft/run_experiment.py
medicraft/trackers/__init__.py
medicraft/trackers/callbacks.py
medicraft/trackers/wandb.py
medicraft/trainers/__init__.py
medicraft/trainers/trainer.py
medicraft/utils/__init__.py
medicraft/utils/artifact_utilities.py
medicraft/utils/files_managment.py
medicraft/utils/transforms.py
medicraft/validation/__init__.py
medicraft/validation/embeddings.py
medicraft-0.9.3.dist-info/LICENSE
medicraft-0.9.3.dist-info/WHEEL
medicraft-0.9.3.dist-info/METADATA
medicraft-0.9.3.dist-info/RECORD
