Metadata-Version: 2.1
Name: medicraft
Version: 0.9.3
Summary: Medicraft synthetic dataset generator
Home-page: https://github.com/drfifonz/medicraft
License: MIT
Keywords: diffusion,generating,medical,images,synthetic dataset,pytorch,torch,diffusion,denoising
Author: Filip Patyk
Author-email: fp.patyk@gmail.com
Requires-Python: >=3.11,<4.0
Classifier: Development Status :: 4 - Beta
Classifier: Environment :: GPU :: NVIDIA CUDA :: 12
Classifier: License :: OSI Approved :: MIT License
Classifier: Programming Language :: Python :: 3
Classifier: Programming Language :: Python :: 3.11
Classifier: Topic :: Scientific/Engineering :: Artificial Intelligence
Classifier: Topic :: Scientific/Engineering :: Image Processing
Requires-Dist: PyYAML (==6.0.1)
Requires-Dist: denoising-diffusion-pytorch (==1.9.4)
Requires-Dist: ema-pytorch (==0.3.1)
Requires-Dist: lightning (==2.2.1)
Requires-Dist: matplotlib (==3.8.4)
Requires-Dist: pandas (==2.2.2)
Requires-Dist: pillow (==10.3.0)
Requires-Dist: pydantic (==2.7.2)
Requires-Dist: scikit-learn (==1.4.2)
Requires-Dist: seaborn (==0.13.2)
Requires-Dist: torch (>=2.1.1,<3.0.0)
Requires-Dist: torchmetrics (==1.3.1)
Requires-Dist: torchvision (>=0.16.1,<0.17.0)
Requires-Dist: tqdm (==4.66.2)
Requires-Dist: umap-learn (==0.5.5)
Requires-Dist: wandb (==0.16.3)
Project-URL: Documentation, https://drfifonz.github.io/medicraft/
Project-URL: Repository, https://github.com/drfifonz/medicraft
